btl2cap/__init__.py
btl2cap/bluez_l2cap.py
btl2cap/client.py
btl2cap/client_fuzz.py
btl2cap/frames.py
btl2cap/fuzz.py
btl2cap/l2cap.py
btl2cap/server.py
btl2cap/server_fuzz.py
btl2cap/lib/libl2cap.so
btl2cap/pytransform/__init__.py
btl2cap/pytransform/platforms/linux/aarch64/_pytransform.so
btl2cap/pytransform/platforms/linux/x86_64/_pytransform.so
btl2cap-0.0.11.dist-info/LICENSE.txt
btl2cap-0.0.11.dist-info/METADATA
btl2cap-0.0.11.dist-info/WHEEL
btl2cap-0.0.11.dist-info/top_level.txt
btl2cap-0.0.11.dist-info/RECORD
