Metadata-Version: 2.1
Name: btl2cap
Version: 0.0.11
Summary: Bluetooth L2CAP Utilities
Home-page: https://pypi.org/project/btl2cap
Author: Cibo
Author-email: cibo@bio-electric.com
License: Proprietary
Classifier: Operating System :: POSIX :: Linux
Classifier: Programming Language :: Python :: 3
Classifier: Programming Language :: Python :: 3 :: Only
Classifier: Programming Language :: Python :: 3.10
Classifier: License :: Other/Proprietary License
Requires-Python: ==3.10.*
License-File: LICENSE.txt
Requires-Dist: bthci (>=0.0.43)
Requires-Dist: xpycommon (>=0.0.24)
